flask_keyvault/__init__.py
flask_keyvault/exceptions.py
flask_keyvault/version.py
Flask_KeyVault-0.6.0.dist-info/LICENSE
Flask_KeyVault-0.6.0.dist-info/METADATA
Flask_KeyVault-0.6.0.dist-info/WHEEL
Flask_KeyVault-0.6.0.dist-info/top_level.txt
Flask_KeyVault-0.6.0.dist-info/RECORD
