Metadata-Version: 2.1
Name: Flask-KeyVault
Version: 0.6.0
Summary: Flask extension to read and write secrets from Azure Key Vault
Home-page: https://github.com/erikhoward/flask-keyvault
Author: Erik Howard
Author-email: erikhoward@protonmail.com
License: MIT
Keywords: flask,azure,keyvault,secrets
Platform: any
Classifier: Development Status :: 4 - Beta
Classifier: Environment :: Web Environment
Classifier: Framework :: Flask
Classifier: Intended Audience :: Developers
Classifier: License :: OSI Approved :: MIT License
Classifier: Operating System :: OS Independent
Classifier: Programming Language :: Python
Classifier: Programming Language :: Python :: 3
Classifier: Programming Language :: Python :: 3.4
Classifier: Programming Language :: Python :: 3.5
Classifier: Programming Language :: Python :: 3.6
Classifier: Programming Language :: Python :: 3.7
Classifier: Topic :: Internet :: WWW/HTTP :: Dynamic Content
Classifier: Topic :: Software Development :: Libraries :: Python Modules
Requires-Dist: Flask
Requires-Dist: azure-keyvault
